teleconnector/__init__.py
teleconnector/exceptions.py
teleconnector/file.py
teleconnector/group.py
teleconnector/terminal.py
teleconnector-1.1.3.dist-info/METADATA
teleconnector-1.1.3.dist-info/WHEEL
teleconnector-1.1.3.dist-info/top_level.txt
teleconnector-1.1.3.dist-info/RECORD
